{
    "features": [
        {
            "feature_type": "building",
            "geometry": null,
            "id": "26f04b4f-9ae2-45e3-99d1-393c66d58eb4",
            "properties": {
                "address_id": "e105efb7-b0d1-4144-8b8e-72eadf95724f",
                "alt_name": null,
                "category": "unspecified",
                "display_point": {
                    "coordinates": [-81.68046983530989, 36.21428142707768],
                    "type": "Point"
                },
                "name": {
                    "en": "Anne Belk Hall"
                },
                "restriction": null
            },
            "type": "Feature"
        }
    ],
    "name": "building",
    "type": "FeatureCollection"
}
